[
  {
    "from": "Delhi",
    "to": "Agra",
    "destination": "Agra",
    "image": "https://tse3.mm.bing.net/th?id=OIP.-CDDfLZYME9QXzMyV1f8wQHaE8&pid=Api&P=0&h=180",
    "estimatedCost": 756,
    "actualCost": 801
  },
  {
    "from": "Mumbai",
    "to": "Pune",
    "destination": "Pune",
    "image": "https://tse1.mm.bing.net/th?id=OIP.dtNuq3zISby7QtZ-xcrSqwHaDt&pid=Api&P=0&h=180",
    "estimatedCost": 659,
    "actualCost": 681
  },
  {
    "from": "Bengaluru",
    "to": "Mysore",
    "destination": "Mysore",
    "image": "https://tse4.mm.bing.net/th?id=OIP.zw65qV5IOVwy9iH4LS3OGQHaDm&pid=Api&P=0&h=180",
    "estimatedCost": 741,
    "actualCost": 705
  },
  {
    "from": "Chennai",
    "to": "Coimbatore",
    "destination": "Coimbatore",
    "image": "https://assets-news.housing.com/news/wp-content/uploads/2022/07/21234906/Coimbatore1.jpg",
    "estimatedCost": 342,
    "actualCost": 337
  },
  {
    "from": "Hyderabad",
    "to": "Warangal",
    "destination": "Warangal",
    "image": "https://www.goindigo.in/content/dam/s6web/in/en/assets/Destinations/destinations/hyderabad/073616_T_Prince_charminar-1.jpg",
    "estimatedCost": 541,
    "actualCost": 578
  },
  {
    "from": "Kolkata",
    "to": "Digha",
    "destination": "Digha",
    "image": "https://tse1.mm.bing.net/th?id=OIP.Igfzap1Gc9ito1N52yxiSAHaEK&pid=Api&P=0&h=180",
    "estimatedCost": 773,
    "actualCost": 779
  },
  {
    "from": "Ahmedabad",
    "to": "Surat",
    "destination": "Surat",
    "image": "https://i.ytimg.com/vi/vcXQ43k-JBg/maxresdefault.jpg",
    "estimatedCost": 333,
    "actualCost": 366
  },
  {
    "from": "Jaipur",
    "to": "Jodhpur",
    "destination": "Jodhpur",
    "image": "https://tse2.mm.bing.net/th?id=OIP.KQ0tpdd2dkXxXo_-VqQORQHaEc&pid=Api&P=0&h=180",
    "estimatedCost": 720,
    "actualCost": 811
  },
  {
    "from": "Lucknow",
    "to": "Varanasi",
    "destination": "Varanasi",
    "image": "https://tse4.mm.bing.net/th?id=OIP.sUzHv_FwRQTYSF53bD78EQHaEK&pid=Api&P=0&h=180",
    "estimatedCost": 362,
    "actualCost": 401
  },
  {
    "from": "Patna",
    "to": "Gaya",
    "destination": "Gaya",
    "image": "https://tse2.mm.bing.net/th?id=OIP.IGVjBVoi7HJ3dil3htcZXwHaEK&pid=Api&P=0&h=180",
    "estimatedCost": 710,
    "actualCost": 687
  },
  {
    "from": "Delhi (copy)",
    "to": "Agra",
    "destination": "Agra",
    "image": "https://tse3.mm.bing.net/th?id=OIP.-CDDfLZYME9QXzMyV1f8wQHaE8&pid=Api&P=0&h=180",
    "estimatedCost": 325,
    "actualCost": 362
  },
  {
    "from": "Hyderabad (copy)",
    "to": "Warangal",
    "destination": "Warangal",
    "image": "https://www.goindigo.in/content/dam/s6web/in/en/assets/Destinations/destinations/hyderabad/073616_T_Prince_charminar-1.jpg",
    "estimatedCost": 650,
    "actualCost": 713
  },
  {
    "from": "Ahmedabad (copy)",
    "to": "Surat",
    "destination": "Surat",
    "image": "https://i.ytimg.com/vi/vcXQ43k-JBg/maxresdefault.jpg",
    "estimatedCost": 391,
    "actualCost": 435
  },
  {
    "from": "Ahmedabad (copy)",
    "to": "Surat",
    "destination": "Surat",
    "image": "https://i.ytimg.com/vi/vcXQ43k-JBg/maxresdefault.jpg",
    "estimatedCost": 638,
    "actualCost": 620
  },
  {
    "from": "Patna (copy)",
    "to": "Gaya",
    "destination": "Gaya",
    "image": "https://tse2.mm.bing.net/th?id=OIP.IGVjBVoi7HJ3dil3htcZXwHaEK&pid=Api&P=0&h=180",
    "estimatedCost": 587,
    "actualCost": 577
  },
  {
    "from": "Mumbai (copy)",
    "to": "Pune",
    "destination": "Pune",
    "image": "https://tse1.mm.bing.net/th?id=OIP.dtNuq3zISby7QtZ-xcrSqwHaDt&pid=Api&P=0&h=180",
    "estimatedCost": 345,
    "actualCost": 440
  },
  {
    "from": "Chennai (copy)",
    "to": "Coimbatore",
    "destination": "Coimbatore",
    "image": "https://assets-news.housing.com/news/wp-content/uploads/2022/07/21234906/Coimbatore1.jpg",
    "estimatedCost": 529,
    "actualCost": 586
  },
  {
    "from": "Hyderabad (copy)",
    "to": "Warangal",
    "destination": "Warangal",
    "image": "https://www.goindigo.in/content/dam/s6web/in/en/assets/Destinations/destinations/hyderabad/073616_T_Prince_charminar-1.jpg",
    "estimatedCost": 723,
    "actualCost": 753
  },
  {
    "from": "Ahmedabad (copy)",
    "to": "Surat",
    "destination": "Surat",
    "image": "https://i.ytimg.com/vi/vcXQ43k-JBg/maxresdefault.jpg",
    "estimatedCost": 409,
    "actualCost": 506
  },
  {
    "from": "Jaipur (copy)",
    "to": "Jodhpur",
    "destination": "Jodhpur",
    "image": "https://tse2.mm.bing.net/th?id=OIP.KQ0tpdd2dkXxXo_-VqQORQHaEc&pid=Api&P=0&h=180",
    "estimatedCost": 508,
    "actualCost": 471
  },
  {
    "from": "Delhi (copy)",
    "to": "Agra",
    "destination": "Agra",
    "image": "https://tse3.mm.bing.net/th?id=OIP.-CDDfLZYME9QXzMyV1f8wQHaE8&pid=Api&P=0&h=180",
    "estimatedCost": 675,
    "actualCost": 639
  },
  {
    "from": "Lucknow (copy)",
    "to": "Varanasi",
    "destination": "Varanasi",
    "image": "https://tse4.mm.bing.net/th?id=OIP.sUzHv_FwRQTYSF53bD78EQHaEK&pid=Api&P=0&h=180",
    "estimatedCost": 598,
    "actualCost": 593
  },
  {
    "from": "Lucknow (copy)",
    "to": "Varanasi",
    "destination": "Varanasi",
    "image": "https://tse4.mm.bing.net/th?id=OIP.sUzHv_FwRQTYSF53bD78EQHaEK&pid=Api&P=0&h=180",
    "estimatedCost": 456,
    "actualCost": 447
  },
  {
    "from": "Jaipur (copy)",
    "to": "Jodhpur",
    "destination": "Jodhpur",
    "image": "https://tse2.mm.bing.net/th?id=OIP.KQ0tpdd2dkXxXo_-VqQORQHaEc&pid=Api&P=0&h=180",
    "estimatedCost": 773,
    "actualCost": 819
  },
  {
    "from": "Bengaluru (copy)",
    "to": "Mysore",
    "destination": "Mysore",
    "image": "https://tse4.mm.bing.net/th?id=OIP.zw65qV5IOVwy9iH4LS3OGQHaDm&pid=Api&P=0&h=180",
    "estimatedCost": 628,
    "actualCost": 705
  },
  {
    "from": "Jaipur (copy)",
    "to": "Jodhpur",
    "destination": "Jodhpur",
    "image": "https://tse2.mm.bing.net/th?id=OIP.KQ0tpdd2dkXxXo_-VqQORQHaEc&pid=Api&P=0&h=180",
    "estimatedCost": 727,
    "actualCost": 799
  },
  {
    "from": "Hyderabad (copy)",
    "to": "Warangal",
    "destination": "Warangal",
    "image": "https://www.goindigo.in/content/dam/s6web/in/en/assets/Destinations/destinations/hyderabad/073616_T_Prince_charminar-1.jpg",
    "estimatedCost": 728,
    "actualCost": 792
  },
  {
    "from": "Bengaluru (copy)",
    "to": "Mysore",
    "destination": "Mysore",
    "image": "https://tse4.mm.bing.net/th?id=OIP.zw65qV5IOVwy9iH4LS3OGQHaDm&pid=Api&P=0&h=180",
    "estimatedCost": 729,
    "actualCost": 774
  },
  {
    "from": "Jaipur (copy)",
    "to": "Jodhpur",
    "destination": "Jodhpur",
    "image": "https://tse2.mm.bing.net/th?id=OIP.KQ0tpdd2dkXxXo_-VqQORQHaEc&pid=Api&P=0&h=180",
    "estimatedCost": 728,
    "actualCost": 773
  },
  {
    "from": "Jaipur (copy)",
    "to": "Jodhpur",
    "destination": "Jodhpur",
    "image": "https://tse2.mm.bing.net/th?id=OIP.KQ0tpdd2dkXxXo_-VqQORQHaEc&pid=Api&P=0&h=180",
    "estimatedCost": 535,
    "actualCost": 580
  },
  {
    "from": "Patna (copy)",
    "to": "Gaya",
    "destination": "Gaya",
    "image": "https://tse2.mm.bing.net/th?id=OIP.IGVjBVoi7HJ3dil3htcZXwHaEK&pid=Api&P=0&h=180",
    "estimatedCost": 503,
    "actualCost": 568
  },
  {
    "from": "Delhi (copy)",
    "to": "Agra",
    "destination": "Agra",
    "image": "https://tse3.mm.bing.net/th?id=OIP.-CDDfLZYME9QXzMyV1f8wQHaE8&pid=Api&P=0&h=180",
    "estimatedCost": 750,
    "actualCost": 826
  },
  {
    "from": "Ahmedabad (copy)",
    "to": "Surat",
    "destination": "Surat",
    "image": "https://i.ytimg.com/vi/vcXQ43k-JBg/maxresdefault.jpg",
    "estimatedCost": 787,
    "actualCost": 870
  },
  {
    "from": "Kolkata (copy)",
    "to": "Digha",
    "destination": "Digha",
    "image": "https://tse1.mm.bing.net/th?id=OIP.Igfzap1Gc9ito1N52yxiSAHaEK&pid=Api&P=0&h=180",
    "estimatedCost": 508,
    "actualCost": 564
  },
  {
    "from": "Lucknow (copy)",
    "to": "Varanasi",
    "destination": "Varanasi",
    "image": "https://tse4.mm.bing.net/th?id=OIP.sUzHv_FwRQTYSF53bD78EQHaEK&pid=Api&P=0&h=180",
    "estimatedCost": 580,
    "actualCost": 588
  },
  {
    "from": "Chennai (copy)",
    "to": "Coimbatore",
    "destination": "Coimbatore",
    "image": "https://assets-news.housing.com/news/wp-content/uploads/2022/07/21234906/Coimbatore1.jpg",
    "estimatedCost": 458,
    "actualCost": 416
  },
  {
    "from": "Delhi (copy)",
    "to": "Agra",
    "destination": "Agra",
    "image": "https://tse3.mm.bing.net/th?id=OIP.-CDDfLZYME9QXzMyV1f8wQHaE8&pid=Api&P=0&h=180",
    "estimatedCost": 679,
    "actualCost": 691
  },
  {
    "from": "Lucknow (copy)",
    "to": "Varanasi",
    "destination": "Varanasi",
    "image": "https://tse4.mm.bing.net/th?id=OIP.sUzHv_FwRQTYSF53bD78EQHaEK&pid=Api&P=0&h=180",
    "estimatedCost": 500,
    "actualCost": 483
  },
  {
    "from": "Chennai (copy)",
    "to": "Coimbatore",
    "destination": "Coimbatore",
    "image": "https://assets-news.housing.com/news/wp-content/uploads/2022/07/21234906/Coimbatore1.jpg",
    "estimatedCost": 672,
    "actualCost": 748
  },
  {
    "from": "Lucknow (copy)",
    "to": "Varanasi",
    "destination": "Varanasi",
    "image": "https://tse4.mm.bing.net/th?id=OIP.sUzHv_FwRQTYSF53bD78EQHaEK&pid=Api&P=0&h=180",
    "estimatedCost": 742,
    "actualCost": 728
  }
]